{"is_source_file": true, "format": "TypeScript React (TSX)", "description": "This file defines UI components related to form handling, including context providers, form fields, labels, controls, and validation message components using React, react-hook-form, and radix-ui.", "external_files": ["@radix-ui/react-label", "@radix-ui/react-slot", "react-hook-form", "@/lib/utils", "@/components/ui/label"], "external_methods": ["cn", "Label"], "published": ["useFormField", "Form", "FormItem", "FormLabel", "FormControl", "FormDescription", "FormMessage", "FormField"], "classes": [], "methods": [{"name": "useFormField", "description": "Custom hook to access form field context and state, providing IDs and validation status."}, {"name": "Form", "description": "Wrapper component using react-hook-form's FormProvider to supply form context."}, {"name": "FormItem", "description": "Component that provides a context for individual form items, enhancing accessibility."}, {"name": "FormLabel", "description": "Component rendering a label for a form field, styled and linked via htmlFor."}, {"name": "FormControl", "description": "Component providing control (e.g., input) with accessibility attributes."}, {"name": "FormDescription", "description": "Component displaying descriptive text for a form field."}, {"name": "FormMessage", "description": "Component displaying validation or error messages related to a form field."}], "calls": ["React.useContext", "React.createContext", "React.forwardRef", "React.useId", "cn", "Label"], "search-terms": ["FormProvider", "FormFieldContext", "react-hook-form", "radix-label", "ui form components", "form validation messaging"], "state": 2, "file_id": 4, "knowledge_revision": 62, "git_revision": "ef5f6bcabc9a017a87ee20c118c10b9528ef5011", "ctags": [], "hash": "1df53cf0afd884a27f799b2ce9917799", "format-version": 4, "code-base-name": "connecto-v1", "filename": "src/components/ui/form.tsx", "revision_history": [{"62": "ef5f6bcabc9a017a87ee20c118c10b9528ef5011"}]}